LICENSE
README.md
setup.py
gaana_scraper/__init__.py
gaana_scraper.egg-info/PKG-INFO
gaana_scraper.egg-info/SOURCES.txt
gaana_scraper.egg-info/dependency_links.txt
gaana_scraper.egg-info/requires.txt
gaana_scraper.egg-info/top_level.txt