Metadata-Version: 2.1
Name: gaana-scraper
Version: 1.0.1
Summary: A python library to scrape gaana
Home-page: UNKNOWN
Author: DataKund
Author-email: datakund@gmail.com
License: Apache License 2.0
Keywords: gaana playlist python bot_studio automation title description singer
Platform: UNKNOWN
License-File: LICENSE
